{"Status": "found", "Wordbase": "LSL4", "Result": [{"Value": "adrenalin|kick", "VariantID": "", "ID": "3000011", "Phonetic": [{"File": "http://lexin.nada.kth.se/sound/v2/869331_1.mp3", "Content": "\u00b2adrenali\u0323:nkik:"}], "Type": "subst.", "Inflection": [{"Form": "best.f.sing.", "Content": "adrenalinkicken"}, {"Form": "obest.f.pl.", "Content": "adrenalinkickar"}, {"Form": "best.f.pl.", "Content": "adrenalinkickarna"}], "Lexeme": [{"VariantID": "", "ID": "90", "Lexemeno": "\u2219", "Definition": {"Content": "tillskott av positiv energi", "ID": "9011084"}, "Example": [{"ID": "3000018", "Content": "publikens st\u00f6d gav hemmalaget en adrenalinkick"}]}]}]}