{"Status": "found", "Wordbase": "LSL4", "Result": [{"Value": "an|stalt", "VariantID": "526", "ID": "1004319", "Phonetic": [{"File": "http://lexin.nada.kth.se/sound/v2/105307_1.mp3", "Content": "\u00b2a\u0323n:stal:t"}], "Type": "subst.", "Inflection": [{"Form": "best.f.sing.", "Content": "anstalten"}, {"Form": "obest.f.pl.", "Content": "anstalter"}, {"Form": "best.f.pl.", "Content": "anstalterna"}], "Lexeme": [{"VariantID": "526", "ID": "597", "Lexemeno": "\u2219", "Definition": {"Content": "institution (ofta f\u00f6r v\u00e5rd eller undervisning), inr\u00e4ttning", "ID": "9011573"}, "Compound": [{"ID": "1004328", "OldID": "200", "Content": "anstalts|v\u00e5rd"}, {"ID": "8017236", "OldID": "198", "Content": "f\u00e5ngv\u00e5rds|anstalt"}, {"ID": "1004330", "Content": "l\u00e4ro|anstalt"}], "Example": [{"ID": "1004326", "Content": "en sluten anstalt"}, {"ID": "1004325", "Content": "han blev intagen p\u00e5 anstalt"}]}]}]}