{"Status": "found", "Wordbase": "LSL4", "Result": [{"Value": "beh\u00e4ftad", "VariantID": "1447", "ID": "1011894", "Phonetic": [{"File": "http://lexin.nada.kth.se/sound/v2/115638_1.mp3", "Content": "behe\u0323f:tad"}], "Type": "adj.", "Inflection": [{"Form": "tform", "Content": "beh\u00e4ftat"}, {"Form": "aform", "Content": "beh\u00e4ftade"}], "Lexeme": [{"VariantID": "1447", "ID": "1663", "Lexemeno": "\u2219", "Definition": {"Content": "som lider av n\u00e5got, belastad", "ID": "9012603"}, "Example": [{"ID": "1011900", "Content": "en metod som \u00e4r beh\u00e4ftad med vissa brister"}]}]}]}