{"Status": "found", "Wordbase": "LSL4", "Result": [{"Value": "br\u00f6d|rost", "VariantID": "2499", "ID": "1020680", "Phonetic": [{"File": "http://lexin.nada.kth.se/sound/v2/127053_1.mp3", "Content": "\u00b2br\u00f6\u0323:dr\u00e5s:t"}], "Type": "subst.", "Inflection": [{"Form": "best.f.sing.", "Content": "br\u00f6drosten"}, {"Form": "obest.f.pl.", "Content": "br\u00f6drostar"}, {"Form": "best.f.pl.", "Content": "br\u00f6drostarna"}], "Lexeme": [{"VariantID": "2499", "ID": "2871", "Lexemeno": "\u2219", "Definition": {"Content": "apparat som rostar br\u00f6d", "ID": "9013787"}, "Illustration": [{"Type": "picture", "Value": "https://bildtema.isof.se/bildetema/bildetema-html5/bildetema.html?version=swedish&languages=swe&page=6&subpage=1"}], "Theme": "6:13", "Example": [{"ID": "8032245", "Content": "hon stoppade tv\u00e5 skivor br\u00f6d i br\u00f6drosten"}]}]}]}