{"Status": "found", "Wordbase": "LSL4", "Result": [{"Value": "b\u00e4ddar", "VariantID": "2645", "ID": "1021715", "Phonetic": [{"File": "http://lexin.nada.kth.se/sound/b0344ddar.mp3", "Content": "\u00b2be\u0323d:ar"}], "Type": "verb", "Inflection": [{"Spec": "att", "Form": "infinitiv", "Content": "b\u00e4dda"}, {"Form": "imperfekt", "Content": "b\u00e4ddade"}, {"Spec": "har", "Form": "supinum", "Content": "b\u00e4ddat"}, {"Spec": "\u00e4r", "Form": "perf.part.", "Content": "b\u00e4ddad"}, {"Spec": "!", "Form": "imperativ", "Content": "b\u00e4dda"}], "Lexeme": [{"VariantID": "2645", "ID": "3052", "Lexemeno": "\u2219", "Definition": {"Content": "g\u00f6r i ordning en s\u00e4ng", "ID": "9013964"}, "Example": [{"ID": "1021725", "Content": "han steg upp, b\u00e4ddade s\u00e4ngen och \u00e5t frukost"}], "Graminfo": [{"ID": "1021723-1", "Order": "1", "Content": "ngn b\u00e4ddar (ngt)"}], "Cycle": [{"CycleID": "5003069", "Comment": {"ID": "5003070", "Type": "general", "Content": "\u00e4ven bildligt"}, "Definition": {"Content": "skapar goda f\u00f6ruts\u00e4ttningar", "ID": "5003071"}, "Example": [{"ID": "8009826", "Content": "hon var i toppform, vilket b\u00e4ddade f\u00f6r en svensk medalj"}], "Graminfo": [{"ID": "8009825-1", "Order": "1", "Content": "ngt b\u00e4ddar f\u00f6r ngt"}]}]}]}, {"Value": "b\u00e4dd", "VariantID": "2644", "ID": "1021706", "Phonetic": [{"File": "http://lexin.nada.kth.se/sound/v2/128868_1.mp3", "Content": "bed:"}], "Type": "subst.", "Inflection": [{"Form": "best.f.sing.", "Content": "b\u00e4dden"}, {"Form": "obest.f.pl.", "Content": "b\u00e4ddar"}, {"Form": "best.f.pl.", "Content": "b\u00e4ddarna"}], "Lexeme": [{"VariantID": "2644", "ID": "3051", "Lexemeno": "\u2219", "Definition": {"Content": "s\u00e4ng, viloplats", "ID": "9013963"}, "Compound": [{"ID": "1021712", "Content": "d\u00f6ds|b\u00e4dd"}, {"ID": "8032265", "OldID": "1037", "Content": "sjuk|b\u00e4dd"}], "Example": [{"ID": "1021713", "Content": "ett vandrarhem med 50 b\u00e4ddar"}]}]}]}