{"Status": "found", "Wordbase": "LSL4", "Result": [{"Value": "del|\u00e4gare", "VariantID": "3061", "ID": "1025259", "Phonetic": [{"File": "http://lexin.nada.kth.se/sound/v2/133715_1.mp3", "Content": "\u00b2de\u0323:l\u00e4:gare"}], "Type": "subst.", "Inflection": [{"Form": "best.f.sing.", "Content": "del\u00e4garen"}, {"Form": "obest.f.pl.", "Content": "del\u00e4gare"}, {"Form": "best.f.pl.", "Content": "del\u00e4garna"}], "Lexeme": [{"VariantID": "3061", "ID": "3555", "Lexemeno": "\u2219", "Definition": {"Content": "person som \u00e4ger en del i ett f\u00f6retag; kompanjon", "ID": "9014456"}}]}]}