{"Status": "found", "Wordbase": "LSL4", "Result": [{"Value": "donation", "VariantID": "3341", "ID": "1027491", "Phonetic": [{"File": "http://lexin.nada.kth.se/sound/v2/137110_1.mp3", "Content": "dona\u0283o\u0323:n"}], "Type": "subst.", "Inflection": [{"Form": "best.f.sing.", "Content": "donationen"}, {"Form": "obest.f.pl.", "Content": "donationer"}, {"Form": "best.f.pl.", "Content": "donationerna"}], "Lexeme": [{"VariantID": "3341", "ID": "3845", "Lexemeno": "\u2219", "Definition": {"Content": "(officiell) g\u00e5va", "ID": "9014739"}, "Example": [{"ID": "8017007", "Content": "museet har f\u00e5tt en stor donation av en konstsamlare"}]}]}]}