{"Status": "found", "Wordbase": "LSL4", "Result": [{"Value": "efter|tr\u00e4dare", "VariantID": "3756", "ID": "1030806", "Phonetic": [{"File": "http://lexin.nada.kth.se/sound/v2/141118_1.mp3", "Content": "\u00b2e\u0323f:ter\u203ftr\u00e4:dare"}], "Type": "subst.", "Inflection": [{"Form": "best.f.sing.", "Content": "eftertr\u00e4daren"}, {"Form": "obest.f.pl.", "Content": "eftertr\u00e4dare"}, {"Form": "best.f.pl.", "Content": "eftertr\u00e4darna"}], "Lexeme": [{"VariantID": "3756", "ID": "4311", "Lexemeno": "\u2219", "Definition": {"Content": "person som \u00f6vertar en annans uppgift", "ID": "9015192"}, "Example": [{"ID": "8016543", "Content": "Mona Sahlin, G\u00f6ran Perssons eftertr\u00e4dare som Socialdemokraternas ledare"}]}]}]}