{"Status": "found", "Wordbase": "LSL4", "Result": [{"Value": "eller", "VariantID": "3857", "ID": "1031620", "Phonetic": [{"File": "http://lexin.nada.kth.se/sound/v2/142423_1.mp3", "Content": "e\u0323l:er"}], "Type": "konj.", "Lexeme": [{"VariantID": "3857", "ID": "4424", "Lexemeno": "\u2219", "Comment": {"ID": "1031623", "Type": "def", "Content": "anger alternativ"}, "Example": [{"ID": "1031625", "OldID": "2283", "Content": "Vill du ha te eller kaffe?"}, {"ID": "1031626", "Content": "100 kronor f\u00f6r en lunch \u2013 det \u00e4r varken dyrt eller billigt"}, {"ID": "8016565", "Content": "Vem var det? \u2013 Jag s\u00e5g inte riktigt, det var antingen Karin eller Tina"}], "Idioms": [{"ID": "1031627", "Content": "Eller hur?", "Definition": {"Content": "Visst har jag r\u00e4tt?; Inte sant?", "ID": "8010230"}}]}]}]}