{"Status": "found", "Wordbase": "LSL4", "Result": [{"Value": "fanatiker", "VariantID": "4227", "ID": "1034485", "Phonetic": [{"File": "http://lexin.nada.kth.se/sound/v2/146677_1.mp3", "Content": "fana\u0323:tiker"}], "Type": "subst.", "Inflection": [{"Form": "best.f.sing.", "Content": "fanatikern"}, {"Form": "obest.f.pl.", "Content": "fanatiker"}, {"Form": "best.f.pl.", "Content": "fanatikerna"}], "Lexeme": [{"VariantID": "4227", "ID": "4840", "Lexemeno": "\u2219", "Definition": {"Content": "fanatisk person", "ID": "9015709"}, "Example": [{"ID": "1034491", "Content": "en religi\u00f6s fanatiker"}]}]}]}