{"Status": "found", "Wordbase": "LSL4", "Result": [{"Value": "fika", "VariantID": "4411", "ID": "1035930", "Phonetic": [{"File": "http://lexin.nada.kth.se/sound/v2/148711_1.mp3", "Content": "\u00b2fi\u0323:ka"}], "Type": "subst.", "Inflection": [{"Form": "best.f.sing.", "Content": "fikat", "Alternate": [{"Spec": "eller", "Content": "fikan"}]}, {"Form": "obest.f.pl.", "Content": "fikor"}, {"Form": "best.f.pl.", "Content": "fikorna"}], "Lexeme": [{"VariantID": "4411", "ID": "5045", "Lexemeno": "\u2219", "Definition": {"Content": "kaffe eller te", "ID": "9015907"}, "Comment": {"ID": "1035936", "Type": "style", "Content": "vardagligt"}, "Compound": [{"ID": "1035937", "OldID": "1762", "Content": "fika|paus"}], "Example": [{"ID": "8018188", "Content": "Ska vi ses p\u00e5 en fika?"}]}]}, {"Value": "fikar", "VariantID": "4412", "ID": "1035939", "Phonetic": [{"File": "http://lexin.nada.kth.se/sound/fikar.mp3", "Content": "\u00b2fi\u0323:kar"}], "Type": "verb", "Inflection": [{"Spec": "att", "Form": "infinitiv", "Content": "fika"}, {"Form": "imperfekt", "Content": "fikade"}, {"Spec": "har", "Form": "supinum", "Content": "fikat"}, {"Form": "perf.part.", "Content": "\u2013"}, {"Spec": "!", "Form": "imperativ", "Content": "fika"}], "Lexeme": [{"VariantID": "4412", "ID": "5047", "Lexemeno": "\u2219", "Definition": {"Content": "dricker kaffe eller te", "ID": "9015909"}, "Comment": {"ID": "1035945", "Type": "style", "Content": "vardagligt"}, "Example": [{"ID": "3003320", "Content": "Nu har vi jobbat i tv\u00e5 timmar, dags att fika!"}], "Graminfo": [{"ID": "1035946-1", "Order": "1", "Content": "ngn fikar"}]}]}]}