{"Status": "found", "Wordbase": "LSL4", "Result": [{"Value": "fri|st\u00e5ende", "VariantID": "4965", "ID": "1040309", "Phonetic": [{"File": "http://lexin.nada.kth.se/sound/v2/156451_1.mp3", "Content": "\u00b2fri\u0323:st\u00e5:ende"}], "Type": "adj., ingen b\u00f6jning", "Lexeme": [{"VariantID": "4965", "ID": "5695", "Lexemeno": "\u2219", "Definition": {"Content": "skild fr\u00e5n \u00f6vriga delar i en helhet", "ID": "9016551"}, "Example": [{"ID": "1040313", "Content": "till huset h\u00f6r ett frist\u00e5ende garage"}]}]}]}