{"Status": "found", "Wordbase": "LSL4", "Result": [{"Value": "f\u00f6r|smak", "VariantID": "5676", "ID": "1046182", "Phonetic": [{"File": "http://lexin.nada.kth.se/sound/v2/164212_1.mp3", "Content": "\u00b2f\u00f6\u0323:r\u203fsma:k"}], "Type": "subst.", "Inflection": [{"Form": "best.f.sing.", "Content": "f\u00f6rsmaken"}, {"Form": "obest.f.pl.", "Content": "\u2013"}, {"Form": "best.f.pl.", "Content": "\u2013"}], "Lexeme": [{"VariantID": "5676", "ID": "6526", "Lexemeno": "\u2219", "Definition": {"Content": "f\u00f6raning, smakprov", "ID": "9017356"}, "Example": [{"ID": "1046188", "Content": "som statist fick hon en f\u00f6rsmak av hur det kunde vara att spela in film"}]}]}]}