{"Status": "found", "Wordbase": "LSL4", "Result": [{"Value": "hygienisk", "VariantID": "7135", "ID": "1058328", "Phonetic": [{"File": "http://lexin.nada.kth.se/sound/v2/186630_1.mp3", "Content": "hygie\u0323:nisk"}], "Type": "adj.", "Inflection": [{"Form": "tform", "Content": "hygieniskt"}, {"Form": "aform", "Content": "hygieniska"}], "Lexeme": [{"VariantID": "7135", "ID": "8239", "Lexemeno": "\u2219", "Definition": {"Content": "som har att g\u00f6ra med hygien; renlig", "ID": "9019017"}, "Example": [{"ID": "1058334", "Content": "restaurangen tvingades st\u00e4nga av hygieniska sk\u00e4l"}]}]}]}