{"Status": "found", "Wordbase": "LSL4", "Result": [{"Value": "h\u00e4kte", "VariantID": "7249", "ID": "1058757", "Phonetic": [{"File": "http://lexin.nada.kth.se/sound/v2/187870_1.mp3", "Content": "\u00b2he\u0323k:te"}], "Type": "subst.", "Inflection": [{"Form": "best.f.sing.", "Content": "h\u00e4ktet"}, {"Form": "obest.f.pl.", "Content": "h\u00e4kten"}, {"Form": "best.f.pl.", "Content": "h\u00e4ktena"}], "Lexeme": [{"VariantID": "7249", "ID": "8376", "Lexemeno": "\u2219", "Definition": {"Content": "(rannsaknings)f\u00e4ngelse f\u00f6r h\u00e4ktade personer", "ID": "9019153"}, "Example": [{"ID": "2002619", "Content": "den berusade mannen fick sitta i h\u00e4kte \u00f6ver natten"}]}]}]}