{"Status": "found", "Wordbase": "LSL4", "Result": [{"Value": "in|fart", "VariantID": "7608", "ID": "1062241", "Phonetic": [{"File": "http://lexin.nada.kth.se/sound/v2/192824_1.mp3", "Content": "\u00b2i\u0323n:fa:r\u203ft"}], "Type": "subst.", "Inflection": [{"Form": "best.f.sing.", "Content": "infarten"}, {"Form": "obest.f.pl.", "Content": "infarter"}, {"Form": "best.f.pl.", "Content": "infarterna"}], "Lexeme": [{"VariantID": "7608", "ID": "8828", "Lexemeno": "\u2219", "Definition": {"Content": "v\u00e4g som leder in till n\u00e5got", "ID": "9019594"}, "Compound": [{"ID": "1062247", "OldID": "3213", "Content": "garage|infart"}], "Example": [{"ID": "8012597", "Content": "s\u00f6dra infarten till Stockholm"}]}]}]}