{"Status": "found", "Wordbase": "LSL4", "Result": [{"Value": "in|kassering", "VariantID": "", "ID": "8012964", "Phonetic": [{"File": "", "Content": "\u00b2i\u0323n:kase:ri\u014b"}], "Type": "subst.", "Inflection": [{"Form": "best.f.sing.", "Content": "inkasseringen"}, {"Form": "obest.f.pl.", "Content": "inkasseringar"}, {"Form": "best.f.pl.", "Content": "inkasseringarna"}], "Lexeme": [{"VariantID": "", "ID": "8904", "Lexemeno": "\u2219", "Definition": {"Content": "handlingen att inkassera n\u00e5got", "ID": "9019669"}}]}]}