{"Status": "found", "Wordbase": "LSL4", "Result": [{"Value": "japanska", "VariantID": "", "ID": "3001464", "Phonetic": [{"File": "http://lexin.nada.kth.se/sound/v2/198194_1.mp3", "Content": "japa\u0323:nska"}], "Type": "subst.", "Inflection": [{"Form": "best.f.sing.", "Content": "japanskan"}, {"Form": "obest.f.pl.", "Content": "japanskor"}, {"Form": "best.f.pl.", "Content": "japanskorna"}], "Lexeme": [{"VariantID": "", "ID": "9301", "Lexemeno": "1", "Definition": {"Content": "kvinna fr\u00e5n Japan", "ID": "9020061"}}, {"VariantID": "", "ID": "9302", "Lexemeno": "2", "Gramcom": {"Content": "endast i singular", "ID": "3001471"}, "Definition": {"Content": "spr\u00e5k i Japan", "ID": "9020062"}}]}, {"Value": "japansk", "VariantID": "7996", "ID": "1065215", "Phonetic": [{"File": "http://lexin.nada.kth.se/sound/v2/198192_1.mp3", "Content": "japa\u0323:nsk"}], "Type": "adj.", "Inflection": [{"Form": "tform", "Content": "japanskt"}, {"Form": "aform", "Content": "japanska"}], "Lexeme": [{"VariantID": "7996", "ID": "9300", "Lexemeno": "\u2219", "Definition": {"Content": "som har att g\u00f6ra med Japan", "ID": "9020060"}}]}]}