{"Status": "found", "Wordbase": "LSL4", "Result": [{"Value": "kemikalier", "VariantID": "8422", "ID": "1068515", "Phonetic": [{"File": "http://lexin.nada.kth.se/sound/v2/206074_1.mp3", "Content": "\u00b2\u00e7emika\u0323:lier"}, {"Spec": "eller", "File": "http://lexin.nada.kth.se/sound/v2/206074_2.mp3", "Content": "\u00e7emika\u0323:lier"}], "Type": "subst. plural", "Inflection": [{"Content": "kemikalierna"}], "Lexeme": [{"VariantID": "8422", "ID": "9798", "Lexemeno": "\u2219", "Definition": {"Content": "kemiskt framst\u00e4llda \u00e4mnen (ofta mer eller mindre farliga)", "ID": "9020542"}, "Example": [{"ID": "3010166", "Content": "kemikalier m\u00e5ste f\u00f6rvaras utom r\u00e4ckh\u00e5ll f\u00f6r barn"}]}]}]}