{"Status": "found", "Wordbase": "LSL4", "Result": [{"Value": "kilo|meter", "VariantID": "8455", "ID": "1068751", "Phonetic": [{"File": "http://lexin.nada.kth.se/sound/v2/206341_1.mp3", "Content": "\u00e7i:lome\u0323:ter"}, {"Spec": "eller", "File": "http://lexin.nada.kth.se/sound/v2/206341_2.mp3", "Content": "ki:lo-"}], "Type": "subst.", "Inflection": [{"Form": "best.f.sing.", "Content": "kilometern"}, {"Form": "obest.f.pl.", "Content": "kilometer", "Alternate": [{"Spec": "eller", "Content": "kilometrar"}]}, {"Form": "best.f.pl.", "Content": "kilometerna", "Alternate": [{"Spec": "eller", "Content": "kilometrarna"}]}], "Abbreviate": {"Content": "km", "ID": "2004007"}, "Lexeme": [{"VariantID": "8455", "ID": "9836", "Lexemeno": "\u2219", "Definition": {"Content": "ett l\u00e4ngdm\u00e5tt (=1\u00a0000 meter)", "ID": "9020579"}, "Theme": "31:62", "Example": [{"ID": "8013821", "Content": "han brukar jogga ett par kilometer varje kv\u00e4ll"}]}]}, {"Value": "km", "VariantID": "8664", "ID": "1070476", "Type": "subst.", "Reference": [{"Type": "see", "Value": "kilometer"}]}]}