{"Status": "found", "Wordbase": "LSL4", "Result": [{"Value": "kn\u00e4pper av", "VariantID": "", "ID": "8013935", "Phonetic": [{"File": "", "Content": "knep:era\u0323:v"}], "Type": "verb", "Inflection": [{"Spec": "att", "Form": "infinitiv", "Content": "kn\u00e4ppa av"}, {"Form": "imperfekt", "Content": "kn\u00e4ppte av"}, {"Spec": "har", "Form": "supinum", "Content": "kn\u00e4ppt av"}, {"Spec": "\u00e4r", "Form": "perf.part.", "Content": "avkn\u00e4ppt"}, {"Spec": "!", "Form": "imperativ", "Content": "kn\u00e4pp av"}], "Lexeme": [{"VariantID": "", "ID": "10190", "Lexemeno": "\u2219", "Definition": {"Content": "st\u00e4nger av genom att trycka p\u00e5 en knapp\u00a0(2)", "ID": "9020929"}, "Example": [{"ID": "8029085", "Content": "hon kn\u00e4ppte av radion"}], "Graminfo": [{"ID": "8029084-1", "Order": "1", "Content": "ngn kn\u00e4pper av ngt"}]}]}]}