{"Status": "found", "Wordbase": "LSL4", "Result": [{"Value": "koloni|stuga", "VariantID": "8836", "ID": "1071853", "Phonetic": [{"File": "http://lexin.nada.kth.se/sound/v2/211131_1.mp3", "Content": "\u00b2k\u00e5l\u00e5ni\u0323:stu:ga"}], "Type": "subst.", "Inflection": [{"Form": "best.f.sing.", "Content": "kolonistugan"}, {"Form": "obest.f.pl.", "Content": "kolonistugor"}, {"Form": "best.f.pl.", "Content": "kolonistugorna"}], "Lexeme": [{"VariantID": "8836", "ID": "10278", "Lexemeno": "\u2219", "Definition": {"Content": "liten stuga p\u00e5 en kolonilott", "ID": "9021018"}}]}]}