{"Status": "found", "Wordbase": "LSL4", "Result": [{"Value": "krasse", "VariantID": "9234", "ID": "1074913", "Phonetic": [{"File": "http://lexin.nada.kth.se/sound/v2/217112_1.mp3", "Content": "\u00b2kra\u0323s:e"}], "Type": "subst.", "Inflection": [{"Form": "best.f.sing.", "Content": "krassen"}, {"Form": "obest.f.pl.", "Content": "\u2013"}, {"Form": "best.f.pl.", "Content": "\u2013"}], "Lexeme": [{"VariantID": "9234", "ID": "10744", "Lexemeno": "\u2219", "Definition": {"Content": "en v\u00e4xt av sl\u00e4ktet Tropaeolum", "ID": "9021475"}}]}, {"Value": "krass", "VariantID": "9233", "ID": "1074905", "Phonetic": [{"File": "http://lexin.nada.kth.se/sound/v2/217110_1.mp3", "Content": "kras:"}], "Type": "adj.", "Inflection": [{"Form": "tform", "Content": "krasst"}, {"Form": "aform", "Content": "krassa"}], "Lexeme": [{"VariantID": "9233", "ID": "10743", "Lexemeno": "\u2219", "Definition": {"Content": "materialistisk", "ID": "9021474"}, "Example": [{"ID": "1074911", "OldID": "5152", "Content": "den krassa verkligheten"}]}]}]}