{"Status": "found", "Wordbase": "LSL4", "Result": [{"Value": "ladu|g\u00e5rd", "VariantID": "9747", "ID": "1078949", "Phonetic": [{"File": "http://lexin.nada.kth.se/sound/v2/224967_1.mp3", "Content": "\u00b2la\u0323:dug\u00e5:r\u203fd"}, {"Spec": "eller", "File": "http://lexin.nada.kth.se/sound/v2/224967_2.mp3", "Content": "la\u0323:g\u00e5:r\u203fd"}], "Alternate": [{"Spec": "eller", "Content": "la|g\u00e5rd", "Phonetic": [{"File": "", "Content": "la\u0323g:\u00e5r\u203fd"}]}], "Type": "subst.", "Inflection": [{"Form": "best.f.sing.", "Content": "ladug\u00e5rden", "Alternate": [{"Content": "lag\u00e5rden"}]}, {"Form": "obest.f.pl.", "Content": "ladug\u00e5rdar", "Alternate": [{"Content": "lag\u00e5rdar"}]}, {"Form": "best.f.pl.", "Content": "ladug\u00e5rdarna", "Alternate": [{"Content": "lag\u00e5rdarna"}]}], "Lexeme": [{"VariantID": "9747", "ID": "11335", "Lexemeno": "\u2219", "Definition": {"Content": "byggnad f\u00f6r kor (p\u00e5 en bondg\u00e5rd)", "ID": "9022056"}, "Illustration": [{"Type": "picture", "Value": "https://bildtema.isof.se/bildetema/bildetema-html5/bildetema.html?version=swedish&languages=swe&page=27&subpage=1"}], "Theme": "29:58"}]}, {"Value": "lag\u00e5rd", "VariantID": "9777", "ID": "1079206", "Phonetic": [{"File": "http://lexin.nada.kth.se/sound/v2/224967_2.mp3", "Content": "la\u0323:g\u00e5:r\u203fd"}], "Type": "subst.", "Reference": [{"Type": "see", "Value": "ladug\u00e5rd"}]}]}