{"Status": "found", "Wordbase": "LSL4", "Result": [{"Value": "mankemang", "VariantID": "10679", "ID": "1086485", "Phonetic": [{"File": "http://lexin.nada.kth.se/sound/v2/238886_1.mp3", "Content": "ma\u014bkema\u0323\u014b:"}], "Type": "subst.", "Inflection": [{"Form": "best.f.sing.", "Content": "mankemanget"}, {"Form": "obest.f.pl.", "Content": "mankemang"}, {"Form": "best.f.pl.", "Content": "mankemangen"}], "Lexeme": [{"VariantID": "10679", "ID": "12451", "Lexemeno": "\u2219", "Definition": {"Content": "trassel\u00a0(1), kr\u00e5ngel", "ID": "9023151"}, "Example": [{"ID": "1086491", "OldID": "5773", "Content": "resan gick utan mankemang"}]}]}]}