{"Status": "found", "Wordbase": "LSL4", "Result": [{"Value": "mellan|ting", "VariantID": "10944", "ID": "1088628", "Phonetic": [{"File": "http://lexin.nada.kth.se/sound/v2/242916_1.mp3", "Content": "\u00b2me\u0323l:anti\u014b:"}], "Type": "subst.", "Inflection": [{"Form": "best.f.sing.", "Content": "mellantinget"}, {"Form": "obest.f.pl.", "Content": "mellanting"}, {"Form": "best.f.pl.", "Content": "mellantingen"}], "Lexeme": [{"VariantID": "10944", "ID": "12765", "Lexemeno": "\u2219", "Definition": {"Content": "korsning, blandning", "ID": "9023460"}, "Example": [{"ID": "1088634", "Content": "filmen \u00e4r ett mellanting mellan komedi och drama"}]}]}]}