{"Status": "found", "Wordbase": "LSL4", "Result": [{"Value": "minder|\u00e5rig", "VariantID": "11049", "ID": "1089485", "Phonetic": [{"File": "http://lexin.nada.kth.se/sound/v2/244784_1.mp3", "Content": "\u00b2mi\u0323n:der\u00e5:rig"}], "Type": "adj.", "Inflection": [{"Form": "tform", "Content": "minder\u00e5rigt"}, {"Form": "aform", "Content": "minder\u00e5riga"}], "Lexeme": [{"VariantID": "11049", "ID": "12896", "Lexemeno": "\u2219", "Definition": {"Content": "(person) som inte fyllt 18 \u00e5r", "ID": "9023591"}, "Example": [{"ID": "1089491", "Content": "de har tv\u00e5 minder\u00e5riga barn"}]}]}]}