{"Status": "found", "Wordbase": "LSL4", "Result": [{"Value": "moralist", "VariantID": "", "ID": "9000347", "Phonetic": [{"File": "http://lexin.nada.kth.se/sound/v2/247784_1.mp3", "Content": "morali\u0323s:t"}], "Type": "subst.", "Inflection": [{"Form": "best.f.sing.", "Content": "moralisten"}, {"Form": "obest.f.pl.", "Content": "moralister"}, {"Form": "best.f.pl.", "Content": "moralisterna"}], "Lexeme": [{"VariantID": "", "ID": "13137", "Lexemeno": "\u2219", "Definition": {"Content": "person som f\u00f6rs\u00f6ker p\u00e5verka andra till moraliskt riktigt handlande", "ID": "9023829"}, "Comment": {"ID": "9000353", "Type": "style", "Content": "ofta n\u00e5got neds\u00e4ttande"}}]}]}