{"Status": "found", "Wordbase": "LSL4", "Result": [{"Value": "n\u00e4mnde|man", "VariantID": "11963", "ID": "1096875", "Phonetic": [{"File": "http://lexin.nada.kth.se/sound/v2/262646_1.mp3", "Content": "\u00b2ne\u0323m:deman:"}, {"Spec": "eller", "File": "http://lexin.nada.kth.se/sound/v2/262646_2.mp3", "Content": "\u00b2ne\u0323m:ndeman:"}], "Type": "subst.", "Inflection": [{"Form": "best.f.sing.", "Content": "n\u00e4mndemannen"}, {"Form": "obest.f.pl.", "Content": "n\u00e4mndem\u00e4n"}, {"Form": "best.f.pl.", "Content": "n\u00e4mndem\u00e4nnen"}], "Lexeme": [{"VariantID": "11963", "ID": "13983", "Lexemeno": "\u2219", "Definition": {"Content": "folkvald medlem i domstol (t.ex. tingsr\u00e4tt)", "ID": "9024648"}}]}]}