{"Status": "found", "Wordbase": "LSL4", "Result": [{"Value": "n\u00e4r|synt", "VariantID": "11995", "ID": "1097165", "Phonetic": [{"File": "http://lexin.nada.kth.se/sound/v2/262947_1.mp3", "Content": "\u00b2n\u00e4\u0323:r\u203fsy:nt"}], "Type": "adj.", "Inflection": [{"Form": "tform", "Content": "n\u00e4rsynt"}, {"Form": "aform", "Content": "n\u00e4rsynta"}], "Lexeme": [{"VariantID": "11995", "ID": "14023", "Lexemeno": "\u2219", "Definition": {"Content": "som ser skarpt och tydligt bara p\u00e5 n\u00e4ra h\u00e5ll", "ID": "9024685"}, "Reference": [{"Type": "antonym", "Value": "l\u00e5ngsynt"}]}]}]}