{"Status": "found", "Wordbase": "LSL4", "Result": [{"Value": "o|sammanh\u00e4ngande", "VariantID": "12617", "ID": "1102437", "Phonetic": [{"File": "http://lexin.nada.kth.se/sound/v2/271781_1.mp3", "Content": "\u00b2o\u0323:sam:anhe\u014b:ande"}], "Type": "adj., ingen b\u00f6jning", "Lexeme": [{"VariantID": "12617", "ID": "14763", "Lexemeno": "\u2219", "Definition": {"Content": "som inte har n\u00e5got inre sammanhang, r\u00f6rig", "ID": "9025409"}, "Example": [{"ID": "1102441", "OldID": "7059", "Content": "en osammanh\u00e4ngande ber\u00e4ttelse"}]}]}]}