{"Status": "found", "Wordbase": "LSL4", "Result": [{"Value": "o|sams", "VariantID": "12618", "ID": "1102444", "Phonetic": [{"File": "http://lexin.nada.kth.se/sound/v2/271791_1.mp3", "Content": "\u00b2o\u0323:sam:s"}], "Type": "adj., ingen b\u00f6jning", "Lexeme": [{"VariantID": "12618", "ID": "14764", "Lexemeno": "\u2219", "Definition": {"Content": "oenig; ov\u00e4nner", "ID": "9025410"}, "Example": [{"ID": "1102451", "Content": "de blev osams med grannarna"}, {"ID": "1102450", "OldID": "7060", "Content": "barnen \u00e4r osams"}], "Graminfo": [{"ID": "1102448-1", "Order": "1", "Content": "ngn \u00e4r osams med ngn"}, {"ID": "1102448-2", "Order": "2", "Content": "n\u00e5gra \u00e4r osams"}]}]}]}