{"Status": "found", "Wordbase": "LSL4", "Result": [{"Value": "pension\u00e4r", "VariantID": "12977", "ID": "1105405", "Phonetic": [{"File": "http://lexin.nada.kth.se/sound/v2/277915_1.mp3", "Content": "pa\u014b\u0283on\u00e4\u0323:r"}, {"Spec": "eller", "File": "http://lexin.nada.kth.se/sound/v2/277915_2.mp3", "Content": "pen-"}], "Type": "subst.", "Inflection": [{"Form": "best.f.sing.", "Content": "pension\u00e4ren"}, {"Form": "obest.f.pl.", "Content": "pension\u00e4rer"}, {"Form": "best.f.pl.", "Content": "pension\u00e4rerna"}], "Lexeme": [{"VariantID": "12977", "ID": "15192", "Lexemeno": "\u2219", "Definition": {"Content": "person som f\u00e5r pension", "ID": "9025831"}, "Compound": [{"ID": "1105412", "Content": "pension\u00e4rs|f\u00f6rening"}, {"ID": "1105413", "OldID": "5134", "Content": "pension\u00e4rs|rabatt"}, {"ID": "9000897", "OldID": "5132", "Content": "sjuk|pension\u00e4r"}, {"ID": "1105415", "OldID": "5131", "Content": "\u00e5lders|pension\u00e4r"}], "Example": [{"ID": "1105411", "Content": "han \u00e4r nybliven pension\u00e4r"}]}]}]}