{"Status": "found", "Wordbase": "LSL4", "Result": [{"Value": "post|giro", "VariantID": "", "ID": "1108631", "Phonetic": [{"File": "http://lexin.nada.kth.se/sound/v2/283897_1.mp3", "Content": "\u00b2p\u00e5\u0323s:tji:ro"}], "Type": "subst.", "Inflection": [{"Form": "best.f.sing.", "Content": "postgirot"}, {"Form": "obest.f.pl.", "Content": "postgiron"}, {"Form": "best.f.pl.", "Content": "postgirona"}], "Lexeme": [{"VariantID": "", "ID": "15634", "Lexemeno": "\u2219", "Definition": {"Content": "(tidigare) konto p\u00e5 Posten f\u00f6r \u00f6verf\u00f6ring av pengar till andra konton (numera ersatt av plusgiro)", "ID": "9026270"}, "Compound": [{"ID": "1108637", "Content": "postgiro|blankett"}]}]}]}