{"Status": "found", "Wordbase": "LSL4", "Result": [{"Value": "pubertet", "VariantID": "13694", "ID": "1111409", "Phonetic": [{"File": "http://lexin.nada.kth.se/sound/v2/288940_1.mp3", "Content": "puber\u203fte\u0323:t"}], "Type": "subst.", "Inflection": [{"Form": "best.f.sing.", "Content": "puberteten"}, {"Form": "obest.f.pl.", "Content": "\u2013"}, {"Form": "best.f.pl.", "Content": "\u2013"}], "Lexeme": [{"VariantID": "13694", "ID": "15995", "Lexemeno": "\u2219", "Definition": {"Content": "period n\u00e4r k\u00f6nsmognaden intr\u00e4der (vanligen i tidiga ton\u00e5r)", "ID": "9026628"}, "Example": [{"ID": "1111415", "Content": "han har kommit in i puberteten och f\u00e5tt gr\u00f6vre r\u00f6st"}]}]}]}