{"Status": "found", "Wordbase": "LSL4", "Result": [{"Value": "redo|g\u00f6relse", "VariantID": "14089", "ID": "1114709", "Phonetic": [{"File": "http://lexin.nada.kth.se/sound/v2/294158_1.mp3", "Content": "\u00b2re\u0323:doj\u00f6:relse"}], "Type": "subst.", "Inflection": [{"Form": "best.f.sing.", "Content": "redog\u00f6relsen"}, {"Form": "obest.f.pl.", "Content": "redog\u00f6relser"}, {"Form": "best.f.pl.", "Content": "redog\u00f6relserna"}], "Lexeme": [{"VariantID": "14089", "ID": "16447", "Lexemeno": "\u2219", "Definition": {"Content": "(l\u00e4ngre) f\u00f6rklarande beskrivning", "ID": "9027076"}, "Compound": [{"ID": "1114716", "OldID": "5592", "Content": "inneh\u00e5lls|redog\u00f6relse"}], "Example": [{"ID": "1114715", "Content": "hon l\u00e4mnade en detaljerad redog\u00f6relse f\u00f6r olyckan"}]}]}]}