{"Status": "found", "Wordbase": "LSL4", "Result": [{"Value": "r\u00e5d|slag", "VariantID": "14765", "ID": "1121156", "Phonetic": [{"File": "http://lexin.nada.kth.se/sound/v2/302469_1.mp3", "Content": "\u00b2r\u00e5\u0323:dsla:g"}], "Type": "subst.", "Inflection": [{"Form": "best.f.sing.", "Content": "r\u00e5dslaget"}, {"Form": "obest.f.pl.", "Content": "r\u00e5dslag"}, {"Form": "best.f.pl.", "Content": "r\u00e5dslagen"}], "Lexeme": [{"VariantID": "14765", "ID": "17175", "Lexemeno": "\u2219", "Definition": {"Content": "\u00f6verl\u00e4ggning, diskussion", "ID": "9027805"}}]}]}