{"Status": "found", "Wordbase": "LSL4", "Result": [{"Value": "salongs|f\u00e4hig", "VariantID": "15024", "ID": "1122424", "Phonetic": [{"File": "http://lexin.nada.kth.se/sound/v2/306005_1.mp3", "Content": "\u00b2sal\u00e5\u0323\u014b:sf\u00e4:ig"}], "Type": "adj.", "Inflection": [{"Form": "tform", "Content": "salongsf\u00e4higt"}, {"Form": "aform", "Content": "salongsf\u00e4higa"}], "Lexeme": [{"VariantID": "15024", "ID": "17452", "Lexemeno": "\u2219", "Definition": {"Content": "som accepteras (i finare kretsar)", "ID": "9028075"}}]}]}