{"Status": "found", "Wordbase": "LSL4", "Result": [{"Value": "sj\u00e4lv|f\u00f6rs\u00f6rjande", "VariantID": "15597", "ID": "1127073", "Phonetic": [{"File": "http://lexin.nada.kth.se/sound/v2/876399_1.mp3", "Content": "\u00b2\u0283e\u0323l:vf\u00f6r\u203fs\u00f6r:jande"}], "Type": "adj., ingen b\u00f6jning", "Lexeme": [{"VariantID": "15597", "ID": "18105", "Lexemeno": "\u2219", "Definition": {"Content": "som klarar sin egen f\u00f6rs\u00f6rjning; som tj\u00e4nar egna pengar", "ID": "9028712"}}]}]}