{"Status": "found", "Wordbase": "LSL4", "Result": [{"Value": "skift|arbetare", "VariantID": "15785", "ID": "1128609", "Phonetic": [{"File": "http://lexin.nada.kth.se/sound/skiftarbetare.mp3", "Content": "\u00b2\u0283i\u0323f:tar:be:tare"}], "Type": "subst.", "Inflection": [{"Form": "best.f.sing.", "Content": "skiftarbetaren"}, {"Form": "obest.f.pl.", "Content": "skiftarbetare"}, {"Form": "best.f.pl.", "Content": "skiftarbetarna"}], "Lexeme": [{"VariantID": "15785", "ID": "18301", "Lexemeno": "\u2219", "Definition": {"Content": "person som arbetar i skift", "ID": "9028903"}}]}]}