{"Status": "found", "Wordbase": "LSL4", "Result": [{"Value": "str\u00e4cker", "VariantID": "17549, 17550", "ID": "1143194", "Phonetic": [{"File": "http://lexin.nada.kth.se/sound/str0344cker.mp3", "Content": "stre\u0323k:er"}], "Type": "verb", "Inflection": [{"Spec": "att", "Form": "infinitiv", "Content": "str\u00e4cka"}, {"Form": "imperfekt", "Content": "str\u00e4ckte"}, {"Spec": "har", "Form": "supinum", "Content": "str\u00e4ckt"}, {"Spec": "\u00e4r", "Form": "perf.part.", "Content": "str\u00e4ckt"}, {"Spec": "!", "Form": "imperativ", "Content": "str\u00e4ck"}], "Lexeme": [{"VariantID": "17549", "ID": "20279", "Lexemeno": "1", "Definition": {"Content": "drar ut n\u00e5got s\u00e5 att det blir l\u00e4ngre", "ID": "9030847"}, "Reference": [{"Type": "animation", "Value": "http://lexin.nada.kth.se/lang/lexinanim/stracker_sig.mp4"}], "Example": [{"ID": "1143204", "Content": "han str\u00e4ckte p\u00e5 halsen f\u00f6r att se b\u00e4ttre"}], "Graminfo": [{"ID": "1143203-1", "Order": "1", "Content": "ngn/ngt str\u00e4cker (p\u00e5) ngt"}], "Idioms": [{"ID": "1143206", "Content": "str\u00e4cker p\u00e5 sig", "Definition": {"Content": "\u00e4r stolt", "ID": "1143207"}}]}, {"VariantID": "17550", "ID": "20280", "Lexemeno": "2", "Definition": {"Content": "r\u00e4cker (handen)", "ID": "9030848"}, "Example": [{"ID": "1143214", "OldID": "9907", "Content": "hon str\u00e4ckte fram handen f\u00f6r att h\u00e4lsa"}], "Graminfo": [{"ID": "5003718-1", "Order": "1", "Content": "ngn str\u00e4cker (fram) ngt"}]}]}]}