{"Status": "found", "Wordbase": "LSL4", "Result": [{"Value": "styrke|t\u00e5r", "VariantID": "17666", "ID": "1144237", "Phonetic": [{"File": "http://lexin.nada.kth.se/sound/v2/346962_1.mp3", "Content": "\u00b2sty\u0323r:ket\u00e5:r"}], "Type": "subst.", "Inflection": [{"Form": "best.f.sing.", "Content": "styrket\u00e5ren"}, {"Form": "obest.f.pl.", "Content": "styrket\u00e5rar"}, {"Form": "best.f.pl.", "Content": "styrket\u00e5rarna"}], "Lexeme": [{"VariantID": "17666", "ID": "20397", "Lexemeno": "\u2219", "Definition": {"Content": "sup", "ID": "9030962"}, "Comment": {"ID": "1144243", "Type": "style", "Content": "vardagligt"}, "Example": [{"ID": "8029966", "Content": "de tog en kopp kaffe med en styrket\u00e5r"}]}]}]}