{"Status": "found", "Wordbase": "LSL4", "Result": [{"Value": "svit", "VariantID": "18020, 18021, 18022", "ID": "1147139", "Phonetic": [{"File": "http://lexin.nada.kth.se/sound/v2/350852_1.mp3", "Content": "svi:t"}], "Type": "subst.", "Inflection": [{"Form": "best.f.sing.", "Content": "sviten"}, {"Form": "obest.f.pl.", "Content": "sviter"}, {"Form": "best.f.pl.", "Content": "sviterna"}], "Lexeme": [{"VariantID": "18020", "ID": "20775", "Lexemeno": "1", "Definition": {"Content": "obruten rad", "ID": "9031330"}, "Compound": [{"ID": "1147146", "OldID": "7004", "Content": "bild|svit"}]}, {"VariantID": "18021", "ID": "20776", "Lexemeno": "2", "Gramcom": {"Content": "endast i plural", "ID": "1147149"}, "Definition": {"Content": "f\u00f6ljd\u00a0(1) av skada eller sjukdom", "ID": "9031331"}, "Example": [{"ID": "1147151", "Content": "hon lider fortfarande av sviterna efter olyckan"}]}, {"VariantID": "18022", "ID": "20777", "Lexemeno": "3", "Definition": {"Content": "exklusiv l\u00e4genhet p\u00e5 hotell", "ID": "9031332"}, "Compound": [{"ID": "1147155", "OldID": "7005", "Content": "lyx|svit"}]}]}]}