{"Status": "found", "Wordbase": "LSL4", "Result": [{"Value": "s\u00e4v", "VariantID": "18338", "ID": "1149333", "Phonetic": [{"File": "http://lexin.nada.kth.se/sound/v2/354368_1.mp3", "Content": "s\u00e4:v"}], "Type": "subst.", "Inflection": [{"Form": "best.f.sing.", "Content": "s\u00e4ven"}, {"Form": "obest.f.pl.", "Content": "\u2013"}, {"Form": "best.f.pl.", "Content": "\u2013"}], "Lexeme": [{"VariantID": "18338", "ID": "21125", "Lexemeno": "\u2219", "Definition": {"Content": "en stor gr\u00e4sliknande v\u00e4xt som v\u00e4xer vid vattendrag", "ID": "9031672"}}]}]}