{"Status": "found", "Wordbase": "LSL4", "Result": [{"Value": "tempor\u00e4r", "VariantID": "18628", "ID": "1152046", "Phonetic": [{"File": "http://lexin.nada.kth.se/sound/v2/358827_1.mp3", "Content": "tempor\u00e4\u0323:r"}], "Type": "adj.", "Inflection": [{"Form": "tform", "Content": "tempor\u00e4rt"}, {"Form": "aform", "Content": "tempor\u00e4ra"}], "Lexeme": [{"VariantID": "18628", "ID": "21473", "Lexemeno": "\u2219", "Definition": {"Content": "som g\u00e4ller f\u00f6r viss tid, tillf\u00e4llig, \u00f6verg\u00e5ende", "ID": "9032018"}, "Reference": [{"Type": "antonym", "Value": "varaktig"}, {"Type": "antonym", "Value": "permanent", "Lemmano": "1"}], "Example": [{"ID": "8007756", "Content": "tabletterna gav bara tempor\u00e4r lindring av sm\u00e4rtan"}]}]}]}