{"Status": "found", "Wordbase": "LSL4", "Result": [{"Value": "tennis", "VariantID": "18634", "ID": "1152091", "Phonetic": [{"File": "http://lexin.nada.kth.se/sound/v2/358913_1.mp3", "Content": "te\u0323n:is"}], "Type": "subst.", "Inflection": [{"Form": "best.f.sing.", "Content": "tennisen"}, {"Form": "obest.f.pl.", "Content": "\u2013"}, {"Form": "best.f.pl.", "Content": "\u2013"}], "Lexeme": [{"VariantID": "18634", "ID": "21479", "Lexemeno": "\u2219", "Definition": {"Content": "ett racketspel f\u00f6r tv\u00e5 (eller fyra) spelare p\u00e5 en ganska stor bana med n\u00e4t", "ID": "9032024"}, "Illustration": [{"Type": "picture", "Value": "https://bildtema.isof.se/bildetema/bildetema-html5/bildetema.html?version=swedish&languages=swe&page=20&subpage=1"}], "Theme": "21:43", "Compound": [{"ID": "1152098", "Content": "tennis|bana"}, {"ID": "8011212", "Content": "tennis|hall"}], "Example": [{"ID": "8007757", "Content": "han spelar tennis en g\u00e5ng i veckan"}]}]}]}