{"Status": "found", "Wordbase": "LSL4", "Result": [{"Value": "tre|steg", "VariantID": "", "ID": "8025198", "Phonetic": [{"File": "http://lexin.nada.kth.se/sound/v2/367664_1.mp3", "Content": "\u00b2tre\u0323:ste:g"}], "Type": "subst.", "Inflection": [{"Form": "best.f.sing.", "Content": "tresteget"}, {"Form": "obest.f.pl.", "Content": "\u2013"}, {"Form": "best.f.pl.", "Content": "\u2013"}], "Lexeme": [{"VariantID": "", "ID": "22115", "Lexemeno": "\u2219", "Definition": {"Content": "en friidrottsgren d\u00e4r man g\u00f6r tre hopp efter varandra", "ID": "9032639"}, "Compound": [{"ID": "8025205", "Content": "trestegs|hopp"}]}]}]}