{"Status": "found", "Wordbase": "LSL4", "Result": [{"Value": "tunn|br\u00f6d", "VariantID": "19440", "ID": "1158606", "Phonetic": [{"File": "http://lexin.nada.kth.se/sound/v2/371356_1.mp3", "Content": "\u00b2tu\u0323n:br\u00f6:d"}], "Type": "subst.", "Inflection": [{"Form": "best.f.sing.", "Content": "tunnbr\u00f6det"}, {"Form": "obest.f.pl.", "Content": "tunnbr\u00f6d"}, {"Form": "best.f.pl.", "Content": "tunnbr\u00f6den"}], "Lexeme": [{"VariantID": "19440", "ID": "22372", "Lexemeno": "\u2219", "Definition": {"Content": "ett br\u00f6d som bakas av kornmj\u00f6lsdeg som kavlas ut i mycket tunna kakor och gr\u00e4ddas", "ID": "9032891"}}]}]}