{"Status": "found", "Wordbase": "LSL4", "Result": [{"Value": "v\u00e5g|l\u00e4ngd", "VariantID": "21074, 21075", "ID": "1173841", "Phonetic": [{"File": "http://lexin.nada.kth.se/sound/v2/393994_1.mp3", "Content": "\u00b2v\u00e5\u0323:gle\u014b:d"}], "Type": "subst.", "Inflection": [{"Form": "best.f.sing.", "Content": "v\u00e5gl\u00e4ngden"}, {"Form": "obest.f.pl.", "Content": "v\u00e5gl\u00e4ngder"}, {"Form": "best.f.pl.", "Content": "v\u00e5gl\u00e4ngderna"}], "Lexeme": [{"VariantID": "21074", "ID": "24219", "Lexemeno": "\u2219", "Definition": {"Content": "l\u00e4ngden p\u00e5 v\u00e5gor (s\u00e4rskilt radiov\u00e5gor)", "ID": "9034698"}, "Idioms": [{"ID": "1173847", "Content": "\u00e4r p\u00e5 samma v\u00e5gl\u00e4ngd", "Definition": {"Content": "tycker och k\u00e4nner likadant", "ID": "1173848"}}]}]}]}