{"Status": "found", "Wordbase": "LSL4", "Result": [{"Value": "ytter|kant", "VariantID": "21410", "ID": "1174556", "Phonetic": [{"File": "http://lexin.nada.kth.se/sound/ytterkant.mp3", "Content": "\u00b2y\u0323t:erkan:t"}], "Type": "subst.", "Inflection": [{"Form": "best.f.sing.", "Content": "ytterkanten"}, {"Form": "obest.f.pl.", "Content": "ytterkanter"}, {"Form": "best.f.pl.", "Content": "ytterkanterna"}], "Lexeme": [{"VariantID": "21410", "ID": "24606", "Lexemeno": "\u2219", "Definition": {"Content": "kant l\u00e4ngst ut", "ID": "9035082"}}]}]}