{"Status": "found", "Wordbase": "LSL4", "Result": [{"Value": "\u00e5nga", "VariantID": "21485", "ID": "1176292", "Phonetic": [{"File": "http://lexin.nada.kth.se/sound/v2/399596_1.mp3", "Content": "\u00b2\u00e5\u0323\u014b:a"}], "Type": "subst.", "Inflection": [{"Form": "best.f.sing.", "Content": "\u00e5ngan"}, {"Form": "obest.f.pl.", "Content": "\u00e5ngor"}, {"Form": "best.f.pl.", "Content": "\u00e5ngorna"}], "Lexeme": [{"VariantID": "21485", "ID": "24695", "Lexemeno": "\u2219", "Definition": {"Content": "(moln av) vatten eller annan v\u00e4tska i gasform", "ID": "9035167"}, "Compound": [{"ID": "1176298", "OldID": "8005", "Content": "vatten|\u00e5nga"}, {"ID": "8014856", "OldID": "8007", "Content": "\u00e5ng|b\u00e5t"}, {"ID": "1176299", "Content": "\u00e5ng|kraft"}, {"ID": "1176300", "OldID": "8006", "Content": "\u00e5ng|maskin"}], "Idioms": [{"ID": "8013417", "Content": "h\u00e5ller \u00e5ngan uppe", "Definition": {"Content": "arbetar h\u00e5rt", "ID": "8013418"}}]}]}, {"Value": "\u00e5ngar", "VariantID": "21486, 21487", "ID": "1176301", "Phonetic": [{"File": "http://lexin.nada.kth.se/sound/0345ngar.mp3", "Content": "\u00b2\u00e5\u0323\u014b:ar"}], "Type": "verb", "Inflection": [{"Spec": "att", "Form": "infinitiv", "Content": "\u00e5nga"}, {"Form": "imperfekt", "Content": "\u00e5ngade"}, {"Spec": "har", "Form": "supinum", "Content": "\u00e5ngat"}, {"Form": "perf.part.", "Content": "\u2013"}, {"Form": "imperativ", "Content": "\u2013"}], "Lexeme": [{"VariantID": "21486", "ID": "24696", "Lexemeno": "1", "Definition": {"Content": "ger ifr\u00e5n sig \u00e5nga, ryker", "ID": "9035168"}, "Example": [{"ID": "1176309", "Content": "\u00e5ngande varm choklad"}, {"ID": "8007566", "Content": "det var s\u00e5 kallt att det \u00e5ngade om dem n\u00e4r de andades"}], "Graminfo": [{"ID": "1176308-1", "Order": "1", "Content": "ngt \u00e5ngar"}, {"ID": "1176308-2", "Order": "2", "Content": "det \u00e5ngar om ngn/ngt"}]}, {"VariantID": "21487", "ID": "24697", "Lexemeno": "2", "Definition": {"Content": "f\u00f6rflyttar sig med hj\u00e4lp av \u00e5ngkraft", "ID": "9035169"}, "Example": [{"ID": "1176314", "OldID": "12121", "Content": "t\u00e5get \u00e5ngade in p\u00e5 stationen"}], "Graminfo": [{"ID": "1176313-1", "Order": "1", "Content": "ngt \u00e5ngar (RIKTNING)"}]}]}]}